lokis_duplicates/__init__.py
lokis_duplicates/finder.py
lokis_duplicates-0.1.0.dist-info/LICENSE
lokis_duplicates-0.1.0.dist-info/METADATA
lokis_duplicates-0.1.0.dist-info/WHEEL
lokis_duplicates-0.1.0.dist-info/top_level.txt
lokis_duplicates-0.1.0.dist-info/RECORD
